parquet_viewer/__init__.py
parquet_viewer/cli.py
parquet_viewer/server.py
parquet_viewer/web/index.html
parquet_viewer/web/vite.svg
parquet_viewer/web/assets/index-CAW19CnX.js
parquet_viewer/web/assets/index-DxtrnQ42.css
parquet_l2_viewer-0.1.1.dist-info/METADATA
parquet_l2_viewer-0.1.1.dist-info/WHEEL
parquet_l2_viewer-0.1.1.dist-info/entry_points.txt
parquet_l2_viewer-0.1.1.dist-info/top_level.txt
parquet_l2_viewer-0.1.1.dist-info/RECORD
