Metadata-Version: 2.4
Name: parquet-l2-viewer
Version: 0.1.1
Summary: Local Parquet L2 Tick Viewer
Requires-Python: >=3.10
Requires-Dist: fastapi>=0.110
Requires-Dist: uvicorn>=0.23
Requires-Dist: duckdb>=0.10
